CHANGELOG.md
CREDITS.md
LICENSE.txt
MANIFEST.in
README.md
setup.py
PySyst/Brightness.py
PySyst/Clipboard.py
PySyst/Downloader.py
PySyst/FileProperties.py
PySyst/Keyboard.py
PySyst/Packages.py
PySyst/Volume.py
PySyst/__init__.py
PySyst.egg-info/PKG-INFO
PySyst.egg-info/SOURCES.txt
PySyst.egg-info/dependency_links.txt
PySyst.egg-info/requires.txt
PySyst.egg-info/top_level.txt
PySyst/UI/MessageBox.py
PySyst/UI/__init__.py
PySyst/assets/SetVol.exe