Metadata-Version: 2.1
Name: PySyst
Version: 1.2.9
Summary: This Python package alters your computer's settings and files and comes with various system-related functions.
Author: Aniketh Chavare
Author-email: anikethchavare@outlook.com
License: Apache License 2.0
Project-URL: Homepage, https://pypi.org/project/PySyst
Project-URL: Repository, https://github.com/anikethchavare/PySyst
Project-URL: Documentation, https://anikethchavare.gitbook.io/pysyst
Project-URL: Download, https://github.com/anikethchavare/PySyst/releases
Project-URL: Changelog, https://github.com/anikethchavare/PySyst/blob/main/CHANGELOG.md
Project-URL: Issues, https://github.com/anikethchavare/PySyst/issues
Classifier: Development Status :: 5 - Production/Stable
Classifier: License :: OSI Approved :: Apache Software License
Classifier: Natural Language :: English
Classifier: Operating System :: Microsoft :: Windows
Classifier: Operating System :: MacOS
Classifier: Operating System :: POSIX :: Linux
Classifier: Programming Language :: Python
Classifier: Programming Language :: Python :: 2
Classifier: Programming Language :: Python :: 3
Classifier: Topic :: Software Development
License-File: LICENSE.txt
Requires-Dist: requests
Requires-Dist: beautifulsoup4
Requires-Dist: colorama
Requires-Dist: pyperclip
Requires-Dist: PyAutoGUI
